{"paths":{},"types":[],"uuids":["24CohJU+hCzK3RDoNqwsVR","df/AwYOIxMhYwcu3Amcnsa","e1QyyCnchF2riWCimYAGeq","18mGh7iMRFGLAtZWpbsxIU","ecpdLyjvZBwrvm+cedCcQy"],"scenes":{"db://assets/project-base/MainScene.fire":1,"db://assets/ymtScripts/yomitoo/first/FirstLoad.fire":0},"redirect":[4,0],"deps":["internal"],"packs":{"0a7d03e2a":[3,1]},"name":"main","importBase":"import","nativeBase":"native","debug":false,"isZip":false,"encrypted":false,"versions":{"import":["0a7d03e2a","13514",0,"d006f",2,"7871f"],"native":[2,"c476d"]}}